importguard/__init__.py
importguard/__main__.py
importguard/cli.py
importguard/config.py
importguard/core.py
importguard/models.py
importguard/parser.py
importguard/py.typed
importguardpy-0.1.0.dist-info/METADATA
importguardpy-0.1.0.dist-info/WHEEL
importguardpy-0.1.0.dist-info/entry_points.txt
importguardpy-0.1.0.dist-info/licenses/LICENSE
importguardpy-0.1.0.dist-info/RECORD
