Metadata-Version: 2.4
Name: importguardpy
Version: 0.1.0
Summary: Measure and enforce import-time behavior in Python projects
Project-URL: Homepage, https://github.com/AryanKumar1401/importguard
Project-URL: Documentation, https://github.com/AryanKumar1401/importguard#readme
Project-URL: Repository, https://github.com/AryanKumar1401/importguard
Project-URL: Issues, https://github.com/AryanKumar1401/importguard/issues
Project-URL: Changelog, https://github.com/AryanKumar1401/importguard/releases
Author: Aryan Kumar
Maintainer: Aryan Kumar
License-Expression: MIT
License-File: LICENSE
Keywords: ci,cli,cold-start,import,lint,performance,profiling,startup,testing,timing
Classifier: Development Status :: 4 - Beta
Classifier: Environment :: Console
Classifier: Intended Audience :: Developers
Classifier: License :: OSI Approved :: MIT License
Classifier: Operating System :: MacOS
Classifier: Operating System :: Microsoft :: Windows
Classifier: Operating System :: OS Independent
Classifier: Operating System :: POSIX :: Linux
Classifier: Programming Language :: Python :: 3
Classifier: Programming Language :: Python :: 3.9
Classifier: Programming Language :: Python :: 3.10
Classifier: Programming Language :: Python :: 3.11
Classifier: Programming Language :: Python :: 3.12
Classifier: Programming Language :: Python :: 3.13
Classifier: Topic :: Software Development :: Build Tools
Classifier: Topic :: Software Development :: Quality Assurance
Classifier: Topic :: Software Development :: Testing
Classifier: Typing :: Typed
Requires-Python: >=3.9
Provides-Extra: dev
Requires-Dist: mypy>=1.0; extra == 'dev'
Requires-Dist: pytest-cov>=4.0; extra == 'dev'
Requires-Dist: pytest>=7.0; extra == 'dev'
Requires-Dist: ruff>=0.1.0; extra == 'dev'
